MyBrowser/DB.py
MyBrowser/__init__.py
MyBrowser/baseChrome.py
MyBrowser/baseFirefox.py
MyBrowser/basicBrowser.py
MyBrowser/myBrowser.py
MyBrowser/myBrowser2.py
MyBrowser/utils.py
MyBrowser/LIB/__init__.py
MyBrowser/LIB/logger.py
MyBrowser/LIB/yaml_read.py
pkycrawtester-0.0.2.dist-info/METADATA
pkycrawtester-0.0.2.dist-info/WHEEL
pkycrawtester-0.0.2.dist-info/top_level.txt
pkycrawtester-0.0.2.dist-info/RECORD
